coco/__init__.py
coco/_parser.py
coco_labels_parser-1.0.1.dist-info/METADATA
coco_labels_parser-1.0.1.dist-info/WHEEL
coco_labels_parser-1.0.1.dist-info/top_level.txt
coco_labels_parser-1.0.1.dist-info/RECORD
