Metadata-Version: 2.1
Name: coco-labels-parser
Version: 1.0.1
Summary: A simple labels parser of COCO dataset.
Home-page: UNKNOWN
Author: Enchanter
Author-email: 409766147@qq.com
License: UNKNOWN
Keywords: coco labels
Platform: UNKNOWN
Classifier: Intended Audience :: Developers
Classifier: Natural Language :: Chinese (Simplified)
Classifier: Programming Language :: Python :: 3.6
Classifier: Topic :: Utilities
